sqlalchemy_dict/__init__.py
sqlalchemy_dict/base_model.py
sqlalchemy_dict/constants.py
sqlalchemy_dict/field.py
sqlalchemy_dict/formatter.py
sqlalchemy_dict/utils.py
sqlalchemy_dict/tests/__init__.py
sqlalchemy_dict/tests/conftest.py
sqlalchemy_dict/tests/db.py
sqlalchemy_dict/tests/test_base_model.py
sqlalchemy_dict/tests/test_utils.py
sqlalchemy_dict-0.7.0.dist-info/LICENSE
sqlalchemy_dict-0.7.0.dist-info/METADATA
sqlalchemy_dict-0.7.0.dist-info/WHEEL
sqlalchemy_dict-0.7.0.dist-info/top_level.txt
sqlalchemy_dict-0.7.0.dist-info/RECORD
