Metadata-Version: 2.1
Name: sqlalchemy-dict
Version: 0.7.0
Summary: sqlalchemy extension for interacting models with python dictionary.
Home-page: https://github.com/meyt/sqlalchemy-dict
Author: Mahdi Ghane.g
Author-email: UNKNOWN
License: MIT License
Platform: UNKNOWN
Classifier: Development Status :: 3 - Alpha
Classifier: License :: OSI Approved :: MIT License
Classifier: Programming Language :: Python :: 3.4
Classifier: Programming Language :: Python :: 3.5
Classifier: Programming Language :: Python :: 3.6
Classifier: Programming Language :: Python :: 3.7
Classifier: Operating System :: OS Independent
Classifier: Topic :: Software Development :: Libraries
Requires-Dist: sqlalchemy
